eu_country_codes.py
pyeucountrycodes-1.3.0.dist-info/LICENSE
pyeucountrycodes-1.3.0.dist-info/WHEEL
pyeucountrycodes-1.3.0.dist-info/METADATA
pyeucountrycodes-1.3.0.dist-info/RECORD
