Metadata-Version: 2.1
Name: pyeucountrycodes
Version: 1.3.0
Summary: All ISO 3166 country codes for EU countries.
Home-page: https://github.com/jugmac00/pyeucountrycodes
Author: Jürgen Gmach
Author-email: juergen.gmach@googlemail.com
Requires-Python: >=3.7
Classifier: License :: OSI Approved :: MIT License
Classifier: Operating System :: OS Independent
Classifier: Programming Language :: Python
Classifier: Programming Language :: Python :: 3.7
Classifier: Programming Language :: Python :: 3.8
Classifier: Programming Language :: Python :: 3.9
Classifier: Programming Language :: Python :: 3.10
Classifier: Programming Language :: Python :: 3.11
Classifier: Topic :: Software Development :: Libraries
